{"_wandb":{"runtime":24},"TD3/best_mean_reward":-79.13034570327028,"setup/algorithm":"td3","setup/features_dim":32,"TD3/current_phase":0,"_timestamp":1.748605943907083e+09,"setup/phases":4,"TD3/replay_buffer_size":9999,"setup/steps_per_phase":90,"TD3/mean_distance_to_targets":2.209324359893799,"setup/total_parameters":629388,"setup/extractor_type":"matrix","TD3/collision_count":0,"setup/episode_length":360,"TD3/episode_reward":-70.97652298212051,"TD3/episode_length":12,"setup/num_drones":1,"time/fps":434,"_step":1858,"global_step":9966,"_runtime":24.656052,"TD3/models_saved":2,"rollout/ep_len_mean":7.07,"TD3/episodes_completed":1414,"TD3/timestep":10000,"TD3/mean_episode_reward_last_100":-79.69708879020065,"rollout/ep_rew_mean":-80.22765}