{"rollout/ep_rew_mean":-99.45257,"eval/mean_ep_length":360,"setup/extractor_parameters":55840,"train/collision_count":0,"_timestamp":1.748447840356523e+09,"setup/episode_length":360,"train/std":2.272045,"train/current_phase":1,"_runtime":2052.478047,"train/episode_length":360,"final_eval/mean_reward":-76.21037595197558,"setup/action_space_shape":[1,63],"train/approx_kl":0.014019897,"setup/action_buffer_size":0,"train/reward_improvement_needed":28.334047693461173,"train/episodes_completed":5280,"setup/obs_shape":[1,63],"final_eval/training_time_seconds":2047.2116041183472,"train/formation_error":0,"setup/num_drones":1,"train/learning_rate":0.0003,"_step":9219,"train/value_loss":10.062127,"setup/extractor_type":"matrix","setup/artifact_save_frequency":25000,"train/mean_episode_reward_last_100":-103.79022183939814,"setup/features_dim":32,"rollout/ep_len_mean":360,"train/timestep":1900000,"train/loss":4.2049747,"time/fps":928,"train/clip_fraction":0.015917968,"final_eval/training_time_minutes":34.12019340197245,"global_step":1900000,"train/current_reward":-0.11294756084680557,"train/clip_range":0.2,"train/explained_variance":0.7205272,"setup/control_frequency":30,"train/policy_gradient_loss":-0.0026310554,"_wandb":{"runtime":2066},"setup/action_type":"PID","eval/mean_reward":-76.251366,"train/mean_distance_to_targets":0.9948855638504028,"train/models_saved_count":161,"train/entropy_loss":-6.7130413,"train/targets_reached":0,"setup/phases":4,"final_eval/std_reward":0.15217543133503683,"setup/total_parameters":68647,"train/episode_reward":-75.62430381029844,"train/best_mean_reward":-76.45617414593697,"setup/steps_per_phase":90}